pyflit/__init__.py
pyflit/flit.py
pyflit-2.3.1.dist-info/LICENSE
pyflit-2.3.1.dist-info/METADATA
pyflit-2.3.1.dist-info/WHEEL
pyflit-2.3.1.dist-info/top_level.txt
pyflit-2.3.1.dist-info/RECORD
