Metadata-Version: 2.1
Name: pyflit
Version: 2.3.1
Summary: PyFlit provides you to add components, pages, and it has many other features.
Home-page: UNKNOWN
Author: Jerit Baiju
Author-email: jeritalumkal@gmail.com
License: MIT
Keywords: add page,addpage,add_page,add component,addcomponent,add_component
Platform: UNKNOWN
Classifier: Development Status :: 5 - Production/Stable
Classifier: Intended Audience :: Developers
Classifier: Topic :: Software Development :: Build Tools
Classifier: License :: OSI Approved :: MIT License
Classifier: Programming Language :: Python :: 3.8
Classifier: Programming Language :: Python :: 3.9
Classifier: Programming Language :: Python :: 3.10
License-File: LICENSE
Requires-Dist: flask
